scraping-0.0.3.dist-info/DESCRIPTION.rst
scraping-0.0.3.dist-info/METADATA
scraping-0.0.3.dist-info/RECORD
scraping-0.0.3.dist-info/WHEEL
scraping-0.0.3.dist-info/metadata.json
scraping-0.0.3.dist-info/top_level.txt
scrapingutils/__init__.py
scrapingutils/util.py
