Metadata-Version: 1.0
Name: scraping
Version: 0.0.3
Summary: 1st python package
Home-page: http://github.com/neocxf/py-starter
Author: Neo Chen
Author-email: neocxf@gmail.com
License: MIT
Platform: UNKNOWN
